<annotation>
	<folder>annotations</folder>
	<filename>298.jpg</filename>
	<path>C:\Users\jared\Documents\Lego Custom Dataset\training data\images\298.jpg</path>
	<source>
		<database>Unknown</database>
	</source>
	<size>
		<width>512</width>
		<height>512</height>
		<depth>3</depth>
	</size>
	<segmented>0</segmented>
	<object>
		<name>3004</name>
		<color>15</color>
		<pose>Unspecified</pose>
		<truncated>0</truncated>
		<difficult>0</difficult>
		<bndbox>
			<xmin>286</xmin>
			<ymin>191</ymin>
			<xmax>351</xmax>
			<ymax>263</ymax>
		</bndbox>
	</object>
	<object>
		<name>3024</name>
		<color>70</color>
		<pose>Unspecified</pose>
		<truncated>0</truncated>
		<difficult>0</difficult>
		<bndbox>
			<xmin>244</xmin>
			<ymin>254</ymin>
			<xmax>282</xmax>
			<ymax>292</ymax>
		</bndbox>
	</object>
	<object>
		<name>3004</name>
		<color>0</color>
		<pose>Unspecified</pose>
		<truncated>0</truncated>
		<difficult>0</difficult>
		<bndbox>
			<xmin>248</xmin>
			<ymin>295</ymin>
			<xmax>284</xmax>
			<ymax>359</ymax>
		</bndbox>
	</object>
	<object>
		<name>3024</name>
		<color>72</color>
		<pose>Unspecified</pose>
		<truncated>0</truncated>
		<difficult>0</difficult>
		<bndbox>
			<xmin>319</xmin>
			<ymin>432</ymin>
			<xmax>351</xmax>
			<ymax>468</ymax>
		</bndbox>
	</object>
</annotation>