<annotation>
	<folder>annotations</folder>
	<filename>371.jpg</filename>
	<path>C:\Users\jared\Documents\Lego Custom Dataset\training data\images\371.jpg</path>
	<source>
		<database>Unknown</database>
	</source>
	<size>
		<width>512</width>
		<height>512</height>
		<depth>3</depth>
	</size>
	<segmented>0</segmented>
	<object>
		<name>3004</name>
		<color>70</color>
		<pose>Unspecified</pose>
		<truncated>0</truncated>
		<difficult>0</difficult>
		<bndbox>
			<xmin>256</xmin>
			<ymin>134</ymin>
			<xmax>324</xmax>
			<ymax>195</ymax>
		</bndbox>
	</object>
	<object>
		<name>3024</name>
		<color>14</color>
		<pose>Unspecified</pose>
		<truncated>0</truncated>
		<difficult>0</difficult>
		<bndbox>
			<xmin>333</xmin>
			<ymin>216</ymin>
			<xmax>374</xmax>
			<ymax>254</ymax>
		</bndbox>
	</object>
	<object>
		<name>3024</name>
		<color>72</color>
		<pose>Unspecified</pose>
		<truncated>0</truncated>
		<difficult>0</difficult>
		<bndbox>
			<xmin>290</xmin>
			<ymin>193</ymin>
			<xmax>321</xmax>
			<ymax>213</ymax>
		</bndbox>
	</object>
	<object>
		<name>3004</name>
		<color>4</color>
		<pose>Unspecified</pose>
		<truncated>0</truncated>
		<difficult>0</difficult>
		<bndbox>
			<xmin>126</xmin>
			<ymin>299</ymin>
			<xmax>194</xmax>
			<ymax>358</ymax>
		</bndbox>
	</object>
	<object>
		<name>3024</name>
		<color>0</color>
		<pose>Unspecified</pose>
		<truncated>0</truncated>
		<difficult>0</difficult>
		<bndbox>
			<xmin>138</xmin>
			<ymin>97</ymin>
			<xmax>179</xmax>
			<ymax>139</ymax>
		</bndbox>
	</object>
</annotation>